{
  "reviewedDate": "2026-06-28",
  "targetCount": 50,
  "products": [
    {
      "product": "Directory Server",
      "requested": 50,
      "collected": 50,
      "rows": [
        {
          "title": "Broken Images in LF12 Help Pages",
          "url": "https://answers.laserfiche.com/questions/226947/Broken-Images-in-LF12-Help-Pages",
          "extractedErrorCodes": [],
          "status": "reviewed-no-code"
        },
        {
          "title": "SAML Authentication using Multiple STS sites?",
          "url": "https://answers.laserfiche.com/questions/160976/SAML-Authentication-using-Multiple-STS-sites",
          "extractedErrorCodes": [],
          "status": "reviewed-no-code"
        },
        {
          "title": "Granting Access to Repository with Educational License",
          "url": "https://answers.laserfiche.com/questions/179015/Granting-Access-to-Repository-with-Educational-License",
          "extractedErrorCodes": [],
          "status": "reviewed-no-code"
        },
        {
          "title": "LFDS-Unable to get information for the machine (LFDS1000)",
          "url": "https://answers.laserfiche.com/questions/190428/LFDSUnable-to-get-information-for-the-machine-LFDS1000",
          "extractedErrorCodes": [],
          "status": "reviewed-no-code"
        },
        {
          "title": "Directory Server STS - How do remove need to manually add users to a group in order to access Forms?",
          "url": "https://answers.laserfiche.com/questions/194978/Directory-Server-STS--How-do-remove-need-to-manually-add-users-to-a-group-in-order-to-access-Forms",
          "extractedErrorCodes": [],
          "status": "reviewed-no-code"
        },
        {
          "title": "Licensing site Detaching automatically when server restarts",
          "url": "https://answers.laserfiche.com/questions/186966/Licensing-site-Detaching-automatically-when-server-restarts",
          "extractedErrorCodes": [],
          "status": "reviewed-no-code"
        },
        {
          "title": "Dynamically assign user task using external database?",
          "url": "https://answers.laserfiche.com/questions/181640/Dynamically-assign-user-task-using-external-database",
          "extractedErrorCodes": [],
          "status": "reviewed-no-code"
        },
        {
          "title": "Linking multiple SAML identity providers through common username",
          "url": "https://answers.laserfiche.com/questions/213876/Linking-multiple-SAML-identity-providers-through-common-username",
          "extractedErrorCodes": [
            "HTTP 404"
          ],
          "status": "candidate"
        },
        {
          "title": "Forms Named User list shows \"invalid\" status for all AD users",
          "url": "https://answers.laserfiche.com/questions/80895/Forms-Named-User-list-shows-invalid-status-for-all-AD-users",
          "extractedErrorCodes": [],
          "status": "reviewed-no-code"
        },
        {
          "title": "Unable to send password reset emails for users",
          "url": "https://answers.laserfiche.com/questions/154071/Unable-to-send-password-reset-emails-for-users",
          "extractedErrorCodes": [],
          "status": "reviewed-no-code"
        },
        {
          "title": "Web Client with STS?",
          "url": "https://answers.laserfiche.com/questions/165079/Web-Client-with-STS",
          "extractedErrorCodes": [],
          "status": "reviewed-no-code"
        },
        {
          "title": "Avante AD integrated LFDS installation, Do not want users to have to enter the domain as part of user name",
          "url": "https://answers.laserfiche.com/questions/198508/Avante-AD-integrated-LFDS-installation-Do-not-want-users-to-have-to-enter-the-domain-as-part-of-user-name",
          "extractedErrorCodes": [],
          "status": "reviewed-no-code"
        },
        {
          "title": "Adding Participants to Forms",
          "url": "https://answers.laserfiche.com/questions/74596/Adding-Participants-to-Forms",
          "extractedErrorCodes": [],
          "status": "reviewed-no-code"
        },
        {
          "title": "Directory Server - What can use a named license besides a User, Device, or Server?",
          "url": "https://answers.laserfiche.com/questions/69202/Directory-Server--What-can-use-a-named-license-besides-a-User-Device-or-Server",
          "extractedErrorCodes": [],
          "status": "reviewed-no-code"
        },
        {
          "title": "Error while using SAML authentication. Authentication method 'X509, MultiFactor'",
          "url": "https://answers.laserfiche.com/questions/207103/Error-while-using-SAML-authentication-Authentication-method-X509-MultiFactor",
          "extractedErrorCodes": [],
          "status": "reviewed-no-code"
        },
        {
          "title": "Why do all AD groups need to be included when using Linked Identity Providers?",
          "url": "https://answers.laserfiche.com/questions/206158/Why-do-all-AD-groups-need-to-be-included-when-using-Linked-Identity-Providers",
          "extractedErrorCodes": [],
          "status": "reviewed-no-code"
        },
        {
          "title": "SAML User Type for Laserfiche Client Login",
          "url": "https://answers.laserfiche.com/questions/199252/SAML-User-Type-for-Laserfiche-Client-Login",
          "extractedErrorCodes": [],
          "status": "reviewed-no-code"
        },
        {
          "title": "identifying attribute in LFDS Proxied Providers dab",
          "url": "https://answers.laserfiche.com/questions/171966/identifying-attribute-in-LFDS-Proxied-Providers-dab",
          "extractedErrorCodes": [],
          "status": "reviewed-no-code"
        },
        {
          "title": "Google SAML Issues - Identity Provider may not configured correctly",
          "url": "https://answers.laserfiche.com/questions/233188/Google-SAML-Issues--Identity-Provider-may-not-configured-correctly",
          "extractedErrorCodes": [],
          "status": "reviewed-no-code"
        },
        {
          "title": "idaptive IDP - SAML will LFDS",
          "url": "https://answers.laserfiche.com/questions/180413/idaptive-IDP--SAML-will-LFDS",
          "extractedErrorCodes": [],
          "status": "reviewed-no-code"
        },
        {
          "title": "Directory Server database",
          "url": "https://answers.laserfiche.com/questions/117487/Directory-Server-database",
          "extractedErrorCodes": [],
          "status": "reviewed-no-code"
        },
        {
          "title": "Okta NotOnOrfter condition is not satisfied",
          "url": "https://answers.laserfiche.com/questions/225583/Okta-NotOnOrfter-condition-is-not-satisfied",
          "extractedErrorCodes": [],
          "status": "reviewed-no-code"
        },
        {
          "title": "SAML with Google",
          "url": "https://answers.laserfiche.com/questions/173112/SAML-with-Google",
          "extractedErrorCodes": [],
          "status": "reviewed-no-code"
        },
        {
          "title": "Directory server xmlendpointutility.exe error",
          "url": "https://answers.laserfiche.com/questions/154642/Directory-server-xmlendpointutilityexe-error",
          "extractedErrorCodes": [],
          "status": "reviewed-no-code"
        },
        {
          "title": "Configure Multiple Entra SSO Applications with a single LFDS site.",
          "url": "https://answers.laserfiche.com/questions/234920/Configure-Multiple-Entra-SSO-Applications-with-a-single-LFDS-site",
          "extractedErrorCodes": [],
          "status": "reviewed-no-code"
        },
        {
          "title": "Feature Request: Hide 'Forgot Password' on LFDSSTS page",
          "url": "https://answers.laserfiche.com/questions/213309/Feature-Request-Hide-Forgot-Password-on-LFDSSTS-page",
          "extractedErrorCodes": [],
          "status": "reviewed-no-code"
        },
        {
          "title": "Active Directory Federation Services - Where does Cloud expect the attribute http://schemas.xmlsoap.org/ws/2005/05/identity/claims/upn to be specified",
          "url": "https://answers.laserfiche.com/questions/201359/Active-Directory-Federation-Services--Where-does-Cloud-expect-the-attribute-httpschemasxmlsoaporgws200505identityclaimsupn-to-be-specified",
          "extractedErrorCodes": [],
          "status": "reviewed-no-code"
        },
        {
          "title": "LDAP query could not be completed error 9357",
          "url": "https://answers.laserfiche.com/questions/134232/LDAP-query-could-not-be-completed-error-9357",
          "extractedErrorCodes": [
            "9357"
          ],
          "status": "candidate"
        },
        {
          "title": "Feature Request: Ability to Test Identity Provider Connection",
          "url": "https://answers.laserfiche.com/questions/201669/Feature-Request-Ability-to-Test-Identity-Provider-Connection",
          "extractedErrorCodes": [],
          "status": "reviewed-no-code"
        },
        {
          "title": "Cannot login to new web access repository",
          "url": "https://answers.laserfiche.com/questions/143920/Cannot-login-to-new-web-access-repository",
          "extractedErrorCodes": [],
          "status": "reviewed-no-code"
        },
        {
          "title": "participant user license not working in Forms",
          "url": "https://answers.laserfiche.com/questions/153663/participant-user-license-not-working-in-Forms",
          "extractedErrorCodes": [],
          "status": "reviewed-no-code"
        },
        {
          "title": "What causes Forms to use SID instead of sAMAccountName for Usernames with Active Directory",
          "url": "https://answers.laserfiche.com/questions/189421/What-causes-Forms-to-use-SID-instead-of-sAMAccountName-for-Usernames-with-Active-Directory",
          "extractedErrorCodes": [],
          "status": "reviewed-no-code"
        },
        {
          "title": "Are you able to Assign Participant Licenses to a Active Directory Security Group",
          "url": "https://answers.laserfiche.com/questions/145428/Are-you-able-to-Assign-Participant-Licenses-to-a-Active-Directory-Security-Group",
          "extractedErrorCodes": [],
          "status": "reviewed-no-code"
        },
        {
          "title": "\"Cannot get user information (LFDS3)\"",
          "url": "https://answers.laserfiche.com/questions/110007/Cannot-get-user-information-LFDS3",
          "extractedErrorCodes": [],
          "status": "reviewed-no-code"
        },
        {
          "title": "LF Cloud Single Sign-On configuration does not look correct to me, fields missing, extra fields not mentioned",
          "url": "https://answers.laserfiche.com/questions/196314/LF-Cloud-Single-SignOn-configuration-does-not-look-correct-to-me-fields--missing-extra-fields-not-mentioned",
          "extractedErrorCodes": [],
          "status": "reviewed-no-code"
        },
        {
          "title": "Bulk import users from Active Directory into Directory Server",
          "url": "https://answers.laserfiche.com/questions/162151/Bulk-import-users-from-Active-Directory-into-Directory-Server",
          "extractedErrorCodes": [],
          "status": "reviewed-no-code"
        },
        {
          "title": "Need assistance with Forms suspending a process",
          "url": "https://answers.laserfiche.com/questions/192536/Need-assistance-with-Forms-suspending-a-process",
          "extractedErrorCodes": [
            "LFF502-UnexpectedError"
          ],
          "status": "candidate"
        },
        {
          "title": "LFDS and AD Synchronisation when user name is changed.",
          "url": "https://answers.laserfiche.com/questions/134502/LFDS-and-AD-Synchronisation-when-user-name-is-changed",
          "extractedErrorCodes": [],
          "status": "reviewed-no-code"
        },
        {
          "title": "Directory Server Settings - License Management?",
          "url": "https://answers.laserfiche.com/questions/179327/Directory-Server-Settings--License-Management",
          "extractedErrorCodes": [],
          "status": "reviewed-no-code"
        },
        {
          "title": "Customize text on web access login screen",
          "url": "https://answers.laserfiche.com/questions/208171/Customize-text-on-web-access-login-screen",
          "extractedErrorCodes": [],
          "status": "reviewed-no-code"
        },
        {
          "title": "Event Viewer Error",
          "url": "https://answers.laserfiche.com/questions/133568/Event-Viewer-Error",
          "extractedErrorCodes": [],
          "status": "reviewed-no-code"
        },
        {
          "title": "Directory Server not sync'ing with Active Directory",
          "url": "https://answers.laserfiche.com/questions/81857/Directory-Server-not-syncing-with-Active-Directory",
          "extractedErrorCodes": [
            "0x80072020"
          ],
          "status": "candidate"
        },
        {
          "title": "Directory Server SOAP security negotiation failed",
          "url": "https://answers.laserfiche.com/questions/170174/Directory-Server-SOAP-security-negotiation-failed",
          "extractedErrorCodes": [],
          "status": "reviewed-no-code"
        },
        {
          "title": "Configuring Forms DMZ server, LFDS not authenticating",
          "url": "https://answers.laserfiche.com/questions/159474/Configuring-Forms-DMZ-server-LFDS-not-authenticating",
          "extractedErrorCodes": [],
          "status": "reviewed-no-code"
        },
        {
          "title": "Forms redirect to LFDS login, which spins and then timeout",
          "url": "https://answers.laserfiche.com/questions/167491/Forms-redirect-to-LFDS-login-which-spins-and-then-timeout",
          "extractedErrorCodes": [],
          "status": "reviewed-no-code"
        },
        {
          "title": "Unable to connect to LFDS for SSO in FormsConfig",
          "url": "https://answers.laserfiche.com/questions/115051/Unable-to-connect-to-LFDS-for-SSO-in-FormsConfig",
          "extractedErrorCodes": [],
          "status": "reviewed-no-code"
        },
        {
          "title": "FaultException: There are too many active security negotiations or secure conversations at the service. Please retry later.",
          "url": "https://answers.laserfiche.com/questions/165217/FaultException-There-are-too-many-active-security-negotiations-or-secure-conversations-at-the-service-Please-retry-later",
          "extractedErrorCodes": [],
          "status": "reviewed-no-code"
        },
        {
          "title": "LFDS SDK - IHasPassswordPolicy - How to use this interface?",
          "url": "https://answers.laserfiche.com/questions/194316/LFDS-SDK--IHasPassswordPolicy--How-to-use-this-interface",
          "extractedErrorCodes": [],
          "status": "reviewed-no-code"
        },
        {
          "title": "LFDS - SAML Identity Provider with Microsoft Graph for group retrieval",
          "url": "https://answers.laserfiche.com/questions/236724/LFDS--SAML-Identity-Provider-with-Microsoft-Graph-for-group-retrieval",
          "extractedErrorCodes": [],
          "status": "reviewed-no-code"
        },
        {
          "title": "Could not set users claims and attributes: Access denied",
          "url": "https://answers.laserfiche.com/questions/70063/Could-not-set-users-claims-and-attributes-Access-denied",
          "extractedErrorCodes": [],
          "status": "reviewed-no-code"
        }
      ]
    }
  ]
}
