{
  "reviewedDate": "2026-07-01",
  "source": "signed-in Chrome Answers search results",
  "targetCount": 50,
  "collected": 50,
  "completedAt": "2026-07-01T18:27:48.385Z",
  "reviewedPages": [
    {
      "query": "\"API Server\" error",
      "page": 2,
      "links": 0
    },
    {
      "query": "\"Quick Fields\" error",
      "page": 2,
      "links": 50
    },
    {
      "query": "\"Import Agent\" error",
      "page": 2,
      "links": 50
    },
    {
      "query": "\"Laserfiche Server\" error",
      "page": 2,
      "error": "Timed out after 10000ms waiting for CDP command Page.navigate."
    },
    {
      "query": "\"Windows Client\" error",
      "page": 2,
      "links": 50
    },
    {
      "query": "WebLink error",
      "page": 2,
      "links": 50
    },
    {
      "query": "Mobile error",
      "page": 2,
      "links": 50
    },
    {
      "query": "Connector error",
      "page": 2,
      "links": 50
    },
    {
      "query": "\"Audit Trail\" error",
      "page": 2,
      "links": 50
    },
    {
      "query": "Snapshot error",
      "page": 2,
      "links": 50
    },
    {
      "query": "error",
      "page": 3,
      "error": "Timed out after 10000ms waiting for CDP command Page.navigate."
    },
    {
      "query": "\"error code\"",
      "page": 3,
      "links": 50
    }
  ],
  "rows": [
    {
      "title": "Quick Fields - Field Error",
      "url": "https://answers.laserfiche.com/questions/84180/Quick-Fields--Field-Error",
      "query": "\"Quick Fields\" error",
      "page": 2,
      "discoveredDate": "2026-07-01",
      "reviewedDate": "2026-07-01",
      "status": "search-result-candidate",
      "notes": "Collected from signed-in Chrome Answers search results; detail page still needs review before promotion."
    },
    {
      "title": "Quick Fields Report",
      "url": "https://answers.laserfiche.com/questions/115299/Quick-Fields-Report",
      "query": "\"Quick Fields\" error",
      "page": 2,
      "discoveredDate": "2026-07-01",
      "reviewedDate": "2026-07-01",
      "status": "search-result-candidate",
      "notes": "Collected from signed-in Chrome Answers search results; detail page still needs review before promotion."
    },
    {
      "title": "Quickfields Agent for Rio",
      "url": "https://answers.laserfiche.com/questions/43835/Quickfields-Agent-for-Rio",
      "query": "\"Quick Fields\" error",
      "page": 2,
      "discoveredDate": "2026-07-01",
      "reviewedDate": "2026-07-01",
      "status": "search-result-candidate",
      "notes": "Collected from signed-in Chrome Answers search results; detail page still needs review before promotion."
    },
    {
      "title": "CLASS",
      "url": "https://answers.laserfiche.com/questions/66497/CLASS",
      "query": "\"Quick Fields\" error",
      "page": 2,
      "discoveredDate": "2026-07-01",
      "reviewedDate": "2026-07-01",
      "status": "search-result-candidate",
      "notes": "Collected from signed-in Chrome Answers search results; detail page still needs review before promotion."
    },
    {
      "title": "Import Agent 10.3 Upgrade Lic Error",
      "url": "https://answers.laserfiche.com/questions/133775/Import-Agent-103-Upgrade-Lic-Error",
      "query": "\"Import Agent\" error",
      "page": 2,
      "discoveredDate": "2026-07-01",
      "reviewedDate": "2026-07-01",
      "status": "search-result-candidate",
      "notes": "Collected from signed-in Chrome Answers search results; detail page still needs review before promotion."
    },
    {
      "title": "Import Agent creating random blank documents",
      "url": "https://answers.laserfiche.com/questions/52300/Import-Agent-creating-random-blank-documents",
      "query": "\"Import Agent\" error",
      "page": 2,
      "discoveredDate": "2026-07-01",
      "reviewedDate": "2026-07-01",
      "status": "search-result-candidate",
      "notes": "Collected from signed-in Chrome Answers search results; detail page still needs review before promotion."
    },
    {
      "title": "Will the Advanced Metadata Ever Be Available in Snapshot?",
      "url": "https://answers.laserfiche.com/questions/232921/Will-the-Advanced-Metadata-Ever-Be-Available-in-Snapshot",
      "query": "\"Windows Client\" error",
      "page": 2,
      "discoveredDate": "2026-07-01",
      "reviewedDate": "2026-07-01",
      "status": "search-result-candidate",
      "notes": "Collected from signed-in Chrome Answers search results; detail page still needs review before promotion."
    },
    {
      "title": "Connector : invalid field on chrome",
      "url": "https://answers.laserfiche.com/questions/185664/Connector--invalid-field-on-chrome",
      "query": "\"Windows Client\" error",
      "page": 2,
      "discoveredDate": "2026-07-01",
      "reviewedDate": "2026-07-01",
      "status": "search-result-candidate",
      "notes": "Collected from signed-in Chrome Answers search results; detail page still needs review before promotion."
    },
    {
      "title": "Search Repository Issue",
      "url": "https://answers.laserfiche.com/questions/222084/Search-Repository-Issue",
      "query": "\"Windows Client\" error",
      "page": 2,
      "discoveredDate": "2026-07-01",
      "reviewedDate": "2026-07-01",
      "status": "search-result-candidate",
      "notes": "Collected from signed-in Chrome Answers search results; detail page still needs review before promotion."
    },
    {
      "title": "WebLink Launching error",
      "url": "https://answers.laserfiche.com/questions/65753/WebLink-Launching-error",
      "query": "WebLink error",
      "page": 2,
      "discoveredDate": "2026-07-01",
      "reviewedDate": "2026-07-01",
      "status": "search-result-candidate",
      "notes": "Collected from signed-in Chrome Answers search results; detail page still needs review before promotion."
    },
    {
      "title": "Object reference not set to an instance of an object",
      "url": "https://answers.laserfiche.com/questions/90286/Object-reference-not-set-to-an-instance-of-an-object",
      "query": "WebLink error",
      "page": 2,
      "discoveredDate": "2026-07-01",
      "reviewedDate": "2026-07-01",
      "status": "search-result-candidate",
      "notes": "Collected from signed-in Chrome Answers search results; detail page still needs review before promotion."
    },
    {
      "title": "Best Tips for getting access back for Weblink",
      "url": "https://answers.laserfiche.com/questions/186994/Best-Tips-for-getting-access-back-for-Weblink",
      "query": "WebLink error",
      "page": 2,
      "discoveredDate": "2026-07-01",
      "reviewedDate": "2026-07-01",
      "status": "search-result-candidate",
      "notes": "Collected from signed-in Chrome Answers search results; detail page still needs review before promotion."
    },
    {
      "title": "weblink Docviewer.asp error message",
      "url": "https://answers.laserfiche.com/questions/160016/weblink-Docviewerasp-error-message",
      "query": "WebLink error",
      "page": 2,
      "discoveredDate": "2026-07-01",
      "reviewedDate": "2026-07-01",
      "status": "search-result-candidate",
      "notes": "Collected from signed-in Chrome Answers search results; detail page still needs review before promotion."
    },
    {
      "title": "Weblink clear cookies required after version 11 upgrade to view PDF's properly",
      "url": "https://answers.laserfiche.com/questions/196538/Weblink-clear-cookies-required-after-version-11-upgrade-to-view-PDFs-properly",
      "query": "WebLink error",
      "page": 2,
      "discoveredDate": "2026-07-01",
      "reviewedDate": "2026-07-01",
      "status": "search-result-candidate",
      "notes": "Collected from signed-in Chrome Answers search results; detail page still needs review before promotion."
    },
    {
      "title": "Attempted to Read or Write Protected Memory",
      "url": "https://answers.laserfiche.com/questions/93574/Attempted-to-Read-or-Write-Protected-Memory",
      "query": "WebLink error",
      "page": 2,
      "discoveredDate": "2026-07-01",
      "reviewedDate": "2026-07-01",
      "status": "search-result-candidate",
      "notes": "Collected from signed-in Chrome Answers search results; detail page still needs review before promotion."
    },
    {
      "title": "Weblink stream file size limit",
      "url": "https://answers.laserfiche.com/questions/147923/Weblink-stream-file-size-limit",
      "query": "WebLink error",
      "page": 2,
      "discoveredDate": "2026-07-01",
      "reviewedDate": "2026-07-01",
      "status": "search-result-candidate",
      "notes": "Collected from signed-in Chrome Answers search results; detail page still needs review before promotion."
    },
    {
      "title": "MismatchedFingerprint error",
      "url": "https://answers.laserfiche.com/questions/56236/MismatchedFingerprint-error",
      "query": "WebLink error",
      "page": 2,
      "discoveredDate": "2026-07-01",
      "reviewedDate": "2026-07-01",
      "status": "search-result-candidate",
      "notes": "Collected from signed-in Chrome Answers search results; detail page still needs review before promotion."
    },
    {
      "title": "Error - Mobile Front Camera NOT working in Mobile App",
      "url": "https://answers.laserfiche.com/questions/159211/Error--Mobile-Front-Camera-NOT-working-in-Mobile-App",
      "query": "Mobile error",
      "page": 2,
      "discoveredDate": "2026-07-01",
      "reviewedDate": "2026-07-01",
      "status": "search-result-candidate",
      "notes": "Collected from signed-in Chrome Answers search results; detail page still needs review before promotion."
    },
    {
      "title": "Mobile unable to run Business Processes",
      "url": "https://answers.laserfiche.com/questions/154263/Mobile-unable-to-run-Business-Processes",
      "query": "Mobile error",
      "page": 2,
      "discoveredDate": "2026-07-01",
      "reviewedDate": "2026-07-01",
      "status": "search-result-candidate",
      "notes": "Collected from signed-in Chrome Answers search results; detail page still needs review before promotion."
    },
    {
      "title": "Issues Accessing Forms Server LFDS Mobile APP",
      "url": "https://answers.laserfiche.com/questions/120641/Issues-Accessing-Forms-Server-LFDS-Mobile-APP",
      "query": "Mobile error",
      "page": 2,
      "discoveredDate": "2026-07-01",
      "reviewedDate": "2026-07-01",
      "status": "search-result-candidate",
      "notes": "Collected from signed-in Chrome Answers search results; detail page still needs review before promotion."
    },
    {
      "title": "Mobile App Not Loading Gallery",
      "url": "https://answers.laserfiche.com/questions/209616/Mobile-App-Not-Loading-Gallery",
      "query": "Mobile error",
      "page": 2,
      "discoveredDate": "2026-07-01",
      "reviewedDate": "2026-07-01",
      "status": "search-result-candidate",
      "notes": "Collected from signed-in Chrome Answers search results; detail page still needs review before promotion."
    },
    {
      "title": "Connector 10.2 with pop up windows",
      "url": "https://answers.laserfiche.com/questions/134565/Connector-102-with-pop-up-windows",
      "query": "Connector error",
      "page": 2,
      "discoveredDate": "2026-07-01",
      "reviewedDate": "2026-07-01",
      "status": "search-result-candidate",
      "notes": "Collected from signed-in Chrome Answers search results; detail page still needs review before promotion."
    },
    {
      "title": "Connector profiles don't work after Windows 10 update",
      "url": "https://answers.laserfiche.com/questions/164651/Connector-profiles-dont-work-after-Windows-10-update",
      "query": "Connector error",
      "page": 2,
      "discoveredDate": "2026-07-01",
      "reviewedDate": "2026-07-01",
      "status": "search-result-candidate",
      "notes": "Collected from signed-in Chrome Answers search results; detail page still needs review before promotion."
    },
    {
      "title": "Problem with SDK and WebService Restfull",
      "url": "https://answers.laserfiche.com/questions/141392/Problem-with-SDK-and-WebService-Restfull",
      "query": "Connector error",
      "page": 2,
      "discoveredDate": "2026-07-01",
      "reviewedDate": "2026-07-01",
      "status": "search-result-candidate",
      "notes": "Collected from signed-in Chrome Answers search results; detail page still needs review before promotion."
    },
    {
      "title": "Audit Trail Reporting Page is Empty",
      "url": "https://answers.laserfiche.com/questions/236812/Audit-Trail-Reporting-Page-is-Empty",
      "query": "\"Audit Trail\" error",
      "page": 2,
      "discoveredDate": "2026-07-01",
      "reviewedDate": "2026-07-01",
      "status": "search-result-candidate",
      "notes": "Collected from signed-in Chrome Answers search results; detail page still needs review before promotion."
    },
    {
      "title": "Audit Trail Service will not start after server reboot",
      "url": "https://answers.laserfiche.com/questions/141838/Audit-Trail-Service-will-not-start-after-server-reboot",
      "query": "\"Audit Trail\" error",
      "page": 2,
      "discoveredDate": "2026-07-01",
      "reviewedDate": "2026-07-01",
      "status": "search-result-candidate",
      "notes": "Collected from signed-in Chrome Answers search results; detail page still needs review before promotion."
    },
    {
      "title": "\"The Data could not be Loaded\" Message when trying to add Audit Trail User",
      "url": "https://answers.laserfiche.com/questions/110591/The-Data-could-not-be-Loaded-Message-when-trying-to-add-Audit-Trail-User",
      "query": "\"Audit Trail\" error",
      "page": 2,
      "discoveredDate": "2026-07-01",
      "reviewedDate": "2026-07-01",
      "status": "search-result-candidate",
      "notes": "Collected from signed-in Chrome Answers search results; detail page still needs review before promotion."
    },
    {
      "title": "Audit Trail Session Log On Failure",
      "url": "https://answers.laserfiche.com/questions/116049/Audit-Trail-Session-Log-On-Failure",
      "query": "\"Audit Trail\" error",
      "page": 2,
      "discoveredDate": "2026-07-01",
      "reviewedDate": "2026-07-01",
      "status": "search-result-candidate",
      "notes": "Collected from signed-in Chrome Answers search results; detail page still needs review before promotion."
    },
    {
      "title": "Audit Trail Permissions Multiple Domain Environment",
      "url": "https://answers.laserfiche.com/questions/116050/Audit-Trail-Permissions-Multiple-Domain-Environment",
      "query": "\"Audit Trail\" error",
      "page": 2,
      "discoveredDate": "2026-07-01",
      "reviewedDate": "2026-07-01",
      "status": "search-result-candidate",
      "notes": "Collected from signed-in Chrome Answers search results; detail page still needs review before promotion."
    },
    {
      "title": "Translation error and wrong format",
      "url": "https://answers.laserfiche.com/questions/224894/Translation-error-and-wrong-format",
      "query": "\"Audit Trail\" error",
      "page": 2,
      "discoveredDate": "2026-07-01",
      "reviewedDate": "2026-07-01",
      "status": "search-result-candidate",
      "notes": "Collected from signed-in Chrome Answers search results; detail page still needs review before promotion."
    },
    {
      "title": "Snapshot log location?",
      "url": "https://answers.laserfiche.com/questions/220164/Snapshot-log-location",
      "query": "Snapshot error",
      "page": 2,
      "discoveredDate": "2026-07-01",
      "reviewedDate": "2026-07-01",
      "status": "search-result-candidate",
      "notes": "Collected from signed-in Chrome Answers search results; detail page still needs review before promotion."
    },
    {
      "title": "Formatting tokens within Snapshot",
      "url": "https://answers.laserfiche.com/questions/115534/Formatting-tokens-within-Snapshot",
      "query": "Snapshot error",
      "page": 2,
      "discoveredDate": "2026-07-01",
      "reviewedDate": "2026-07-01",
      "status": "search-result-candidate",
      "notes": "Collected from signed-in Chrome Answers search results; detail page still needs review before promotion."
    },
    {
      "title": "Snapshot Profile Manager - Color Profile",
      "url": "https://answers.laserfiche.com/questions/70914/Snapshot-Profile-Manager--Color-Profile",
      "query": "Snapshot error",
      "page": 2,
      "discoveredDate": "2026-07-01",
      "reviewedDate": "2026-07-01",
      "status": "search-result-candidate",
      "notes": "Collected from signed-in Chrome Answers search results; detail page still needs review before promotion."
    },
    {
      "title": "You must have the user management privilege to change privileges. QF4009",
      "url": "https://answers.laserfiche.com/questions/137840/You-must-have-the-user-management-privilege-to-change-privileges-QF4009",
      "query": "\"error code\"",
      "page": 3,
      "discoveredDate": "2026-07-01",
      "reviewedDate": "2026-07-01",
      "status": "search-result-candidate",
      "notes": "Collected from signed-in Chrome Answers search results; detail page still needs review before promotion."
    },
    {
      "title": "Workflow - Try Catch branch",
      "url": "https://answers.laserfiche.com/questions/195622/Workflow--Try-Catch-branch",
      "query": "\"error code\"",
      "page": 3,
      "discoveredDate": "2026-07-01",
      "reviewedDate": "2026-07-01",
      "status": "search-result-candidate",
      "notes": "Collected from signed-in Chrome Answers search results; detail page still needs review before promotion."
    },
    {
      "title": "Start Events giving An unexpected error has occurred. [LFF502-UnexpectedError]",
      "url": "https://answers.laserfiche.com/questions/121341/Start-Events-giving-An-unexpected-error-has-occurred-LFF502UnexpectedError",
      "query": "\"error code\"",
      "page": 3,
      "discoveredDate": "2026-07-01",
      "reviewedDate": "2026-07-01",
      "status": "search-result-candidate",
      "notes": "Collected from signed-in Chrome Answers search results; detail page still needs review before promotion."
    },
    {
      "title": "HTTP request to server error SDK Login",
      "url": "https://answers.laserfiche.com/questions/165596/HTTP-request-to-server-error-SDK-Login",
      "query": "\"error code\"",
      "page": 3,
      "discoveredDate": "2026-07-01",
      "reviewedDate": "2026-07-01",
      "status": "search-result-candidate",
      "notes": "Collected from signed-in Chrome Answers search results; detail page still needs review before promotion."
    },
    {
      "title": "Web Access error code 12145",
      "url": "https://answers.laserfiche.com/questions/67520/Web-Access-error-code-12145",
      "query": "\"error code\"",
      "page": 3,
      "discoveredDate": "2026-07-01",
      "reviewedDate": "2026-07-01",
      "status": "search-result-candidate",
      "notes": "Collected from signed-in Chrome Answers search results; detail page still needs review before promotion."
    },
    {
      "title": "LFAPI and Visual Fox Pro",
      "url": "https://answers.laserfiche.com/questions/66717/LFAPI-and-Visual-Fox-Pro",
      "query": "\"error code\"",
      "page": 3,
      "discoveredDate": "2026-07-01",
      "reviewedDate": "2026-07-01",
      "status": "search-result-candidate",
      "notes": "Collected from signed-in Chrome Answers search results; detail page still needs review before promotion."
    },
    {
      "title": "operation timed out while opening recycle bin",
      "url": "https://answers.laserfiche.com/questions/79629/operation-timed-out-while-opening-recycle-bin",
      "query": "\"error code\"",
      "page": 3,
      "discoveredDate": "2026-07-01",
      "reviewedDate": "2026-07-01",
      "status": "search-result-candidate",
      "notes": "Collected from signed-in Chrome Answers search results; detail page still needs review before promotion."
    },
    {
      "title": "start business process",
      "url": "https://answers.laserfiche.com/questions/82231/start-business-process",
      "query": "\"error code\"",
      "page": 3,
      "discoveredDate": "2026-07-01",
      "reviewedDate": "2026-07-01",
      "status": "search-result-candidate",
      "notes": "Collected from signed-in Chrome Answers search results; detail page still needs review before promotion."
    },
    {
      "title": "Permission Denied",
      "url": "https://answers.laserfiche.com/questions/167801/Permission-Denied",
      "query": "\"error code\"",
      "page": 3,
      "discoveredDate": "2026-07-01",
      "reviewedDate": "2026-07-01",
      "status": "search-result-candidate",
      "notes": "Collected from signed-in Chrome Answers search results; detail page still needs review before promotion."
    },
    {
      "title": "Error 16389 - Windows Accounts non-linked - Effective Rights - Errors Laserfiche 10 .0.0 United Admin Console -",
      "url": "https://answers.laserfiche.com/questions/139391/Error-16389--Windows-Accounts-nonlinked--Effective-Rights--Errors-Laserfiche-10-00-United-Admin-Console-",
      "query": "\"error code\"",
      "page": 3,
      "discoveredDate": "2026-07-01",
      "reviewedDate": "2026-07-01",
      "status": "search-result-candidate",
      "notes": "Collected from signed-in Chrome Answers search results; detail page still needs review before promotion."
    },
    {
      "title": "Capture Workflow error",
      "url": "https://answers.laserfiche.com/questions/129276/Capture-Workflow-error",
      "query": "\"error code\"",
      "page": 3,
      "discoveredDate": "2026-07-01",
      "reviewedDate": "2026-07-01",
      "status": "search-result-candidate",
      "notes": "Collected from signed-in Chrome Answers search results; detail page still needs review before promotion."
    },
    {
      "title": "Business Process Group Permission [0742-WF1]",
      "url": "https://answers.laserfiche.com/questions/149987/Business-Process-Group-Permission-0742WF1",
      "query": "\"error code\"",
      "page": 3,
      "discoveredDate": "2026-07-01",
      "reviewedDate": "2026-07-01",
      "status": "search-result-candidate",
      "notes": "Collected from signed-in Chrome Answers search results; detail page still needs review before promotion."
    },
    {
      "title": "Error HTTP 500.19 - Internal Server Error - Configuring Forms",
      "url": "https://answers.laserfiche.com/questions/117004/Error-HTTP-50019--Internal-Server-Error--Configuring-Forms",
      "query": "\"error code\"",
      "page": 3,
      "discoveredDate": "2026-07-01",
      "reviewedDate": "2026-07-01",
      "status": "search-result-candidate",
      "notes": "Collected from signed-in Chrome Answers search results; detail page still needs review before promotion."
    },
    {
      "title": "send email to microsoft 360 shared mailbox",
      "url": "https://answers.laserfiche.com/questions/119749/send-email-to-microsoft-360-shared-mailbox",
      "query": "\"error code\"",
      "page": 3,
      "discoveredDate": "2026-07-01",
      "reviewedDate": "2026-07-01",
      "status": "search-result-candidate",
      "notes": "Collected from signed-in Chrome Answers search results; detail page still needs review before promotion."
    },
    {
      "title": "ask",
      "url": "https://answers.laserfiche.com/questions/229899/ask",
      "query": "\"error code\"",
      "page": 3,
      "discoveredDate": "2026-07-01",
      "reviewedDate": "2026-07-01",
      "status": "search-result-candidate",
      "notes": "Collected from signed-in Chrome Answers search results; detail page still needs review before promotion."
    },
    {
      "title": "ask",
      "url": "https://answers.laserfiche.com/questions/229901/ask",
      "query": "\"error code\"",
      "page": 3,
      "discoveredDate": "2026-07-01",
      "reviewedDate": "2026-07-01",
      "status": "search-result-candidate",
      "notes": "Collected from signed-in Chrome Answers search results; detail page still needs review before promotion."
    },
    {
      "title": "PDF Text Provider terminating due to an unhandled exception",
      "url": "https://answers.laserfiche.com/questions/215850/PDF-Text-Provider-terminating-due-to-an-unhandled-exception",
      "query": "\"error code\"",
      "page": 3,
      "discoveredDate": "2026-07-01",
      "reviewedDate": "2026-07-01",
      "status": "search-result-candidate",
      "notes": "Collected from signed-in Chrome Answers search results; detail page still needs review before promotion."
    }
  ]
}
